sierra/__init__.py
sierra/main.py
sierra/version.py
sierra/core/__init__.py
sierra/core/batchroot.py
sierra/core/cmdline.py
sierra/core/compare.py
sierra/core/config.py
sierra/core/engine.py
sierra/core/execenv.py
sierra/core/expdef.py
sierra/core/exproot.py
sierra/core/logging.py
sierra/core/plugin.py
sierra/core/proc.py
sierra/core/prod.py
sierra/core/startup.py
sierra/core/storage.py
sierra/core/trampoline.py
sierra/core/types.py
sierra/core/utils.py
sierra/core/vector.py
sierra/core/experiment/__init__.py
sierra/core/experiment/bindings.py
sierra/core/experiment/definition.py
sierra/core/experiment/spec.py
sierra/core/generators/__init__.py
sierra/core/generators/experiment.py
sierra/core/generators/generator_factory.py
sierra/core/graphs/__init__.py
sierra/core/graphs/bcbridge.py
sierra/core/graphs/heatmap.py
sierra/core/graphs/network.py
sierra/core/graphs/pathset.py
sierra/core/graphs/schema.py
sierra/core/graphs/stacked_line.py
sierra/core/graphs/summary_line.py
sierra/core/models/__init__.py
sierra/core/models/info.py
sierra/core/models/interface.py
sierra/core/pipeline/__init__.py
sierra/core/pipeline/pipeline.py
sierra/core/pipeline/yaml.py
sierra/core/pipeline/stage1/__init__.py
sierra/core/pipeline/stage1/pipeline_stage1.py
sierra/core/pipeline/stage2/__init__.py
sierra/core/pipeline/stage2/pipeline_stage2.py
sierra/core/pipeline/stage2/runner.py
sierra/core/pipeline/stage3/__init__.py
sierra/core/pipeline/stage3/gather.py
sierra/core/pipeline/stage3/pipeline_stage3.py
sierra/core/pipeline/stage4/__init__.py
sierra/core/pipeline/stage4/pipeline_stage4.py
sierra/core/pipeline/stage5/__init__.py
sierra/core/pipeline/stage5/pipeline_stage5.py
sierra/core/ros1/__init__.py
sierra/core/ros1/callbacks.py
sierra/core/ros1/cmdline.py
sierra/core/ros1/generators.py
sierra/core/ros1/variables/__init__.py
sierra/core/ros1/variables/exp_setup.py
sierra/core/variables/__init__.py
sierra/core/variables/base_variable.py
sierra/core/variables/batch_criteria.py
sierra_research-1.5.8.dist-info/METADATA
sierra_research-1.5.8.dist-info/WHEEL
sierra_research-1.5.8.dist-info/entry_points.txt
sierra_research-1.5.8.dist-info/licenses/LICENSE
sierra_research-1.5.8.dist-info/RECORD
