Metadata-Version: 2.4
Name: sierra-research
Version: 1.5.8
Summary: Automation framework for the scientific method in R&D
Project-URL: Homepage, https://github.com/jharwell/sierra
Author-email: John Harwell <john.r.harwell@gmail.com>
License: Copyright 2022 John Harwell
License-File: LICENSE
Keywords: agent-based modeling,automation,parameter sweeps,reproducibility,research,reusability,robotics
Classifier: Development Status :: 5 - Production/Stable
Classifier: Environment :: Console
Classifier: Intended Audience :: Developers
Classifier: Intended Audience :: Science/Research
Classifier: Operating System :: MacOS :: MacOS X
Classifier: Operating System :: POSIX :: Linux
Classifier: Programming Language :: Python :: 3.9
Classifier: Programming Language :: Python :: 3.10
Classifier: Programming Language :: Python :: 3.11
Classifier: Programming Language :: Python :: 3.12
Classifier: Topic :: Scientific/Engineering :: Artificial Intelligence
Classifier: Topic :: Scientific/Engineering :: Information Analysis
Classifier: Topic :: Scientific/Engineering :: Visualization
Classifier: Topic :: Software Development :: Libraries :: Application Frameworks
Requires-Python: >=3.9
Requires-Dist: certifi
Requires-Dist: coloredlogs
Requires-Dist: distro
Requires-Dist: haggis
Requires-Dist: hatchling
Requires-Dist: holoviews
Requires-Dist: hvplot
Requires-Dist: implements
Requires-Dist: jsonpath-ng
Requires-Dist: matplotlib
Requires-Dist: networkx
Requires-Dist: numpy<2.0
Requires-Dist: polars
Requires-Dist: prefect
Requires-Dist: prefect[docker]
Requires-Dist: psutil
Requires-Dist: pyarrow
Requires-Dist: pygraphviz
Requires-Dist: pyyaml
Requires-Dist: retry
Requires-Dist: ruamel-yaml
Requires-Dist: strictyaml
Requires-Dist: sympy
Requires-Dist: yamlpath
